README.md
setup.py
pyRoIS_common.egg-info/PKG-INFO
pyRoIS_common.egg-info/SOURCES.txt
pyRoIS_common.egg-info/dependency_links.txt
pyRoIS_common.egg-info/requires.txt
pyRoIS_common.egg-info/top_level.txt
pyrois_common/Component_Sample.py
pyrois_common/Face_Detection.py
pyrois_common/Face_Detection_client.py
pyrois_common/Face_Localization.py
pyrois_common/Face_Localization_client.py
pyrois_common/Follow.py
pyrois_common/Follow_client.py
pyrois_common/Gesture_Recognition.py
pyrois_common/Gesture_Recognition_client.py
pyrois_common/HRI_Engine_client_sample.py
pyrois_common/HRI_Engine_sample.py
pyrois_common/Move.py
pyrois_common/Move_client.py
pyrois_common/Navigation.py
pyrois_common/Navigation_client.py
pyrois_common/Person_Detection.py
pyrois_common/Person_Detection_client.py
pyrois_common/Person_Identification.py
pyrois_common/Person_Identification_client.py
pyrois_common/Person_Localization.py
pyrois_common/Person_Localization_client.py
pyrois_common/Reaction.py
pyrois_common/Reaction_client.py
pyrois_common/Service_Application_Base_sample.py
pyrois_common/Service_Application_IF_sample.py
pyrois_common/Sound_Detection.py
pyrois_common/Sound_Detection_client.py
pyrois_common/Sound_Localization.py
pyrois_common/Sound_Localization_client.py
pyrois_common/Speech_Recognition.py
pyrois_common/Speech_Recognition_client.py
pyrois_common/Speech_Synthesis.py
pyrois_common/Speech_Synthesis_client.py
pyrois_common/System_Information.py
pyrois_common/System_Information_client.py
pyrois_common/__init__.py
pyrois_common/command_message.py
pyrois_common/message_profile.py
tests/__init__.py
tests/command_message_test.py
tests/test00.py
tests/test_execute.py
tests/test_main_sub_engine2.py
tests/test_main_sub_engine3.py
tests/test_main_sub_engine4.py
tests/test_make_xml.py
tests/test_make_xml_2.py
tests/test_search.py
tests/testxml.py
tests/testxml_eng.py
tests/unittest_execute_branch.py
tests/unittest_execute_branch_error.py
tests/unittest_execute_multi_commands.py
tests/unittest_execute_multi_components.py
tests/utils.py