Metadata-Version: 2.1
Name: pyRoIS-common
Version: 0.1.6
Summary: Implementation of HRI Engine on RoIS Framework in Python
Home-page: https://inohira.mns.kyutech.ac.jp/git/inohira/pyRoIS-higashi
Author: Eiichi Inohira
Author-email: inohira.eiichi402@mail.kyutech.jp
License: UNKNOWN
Platform: UNKNOWN
Classifier: Programming Language :: Python :: 3
Classifier: License :: OSI Approved :: MIT License
Classifier: Operating System :: OS Independent
